gocomics_downloader/__init__.py
gocomics_downloader/constants.py
gocomics_downloader/downloader.py
gocomics_downloader/exceptions.py
gocomics_downloader/parser.py
gocomics_downloader-1.1.1.3.dist-info/DESCRIPTION.rst
gocomics_downloader-1.1.1.3.dist-info/METADATA
gocomics_downloader-1.1.1.3.dist-info/RECORD
gocomics_downloader-1.1.1.3.dist-info/WHEEL
gocomics_downloader-1.1.1.3.dist-info/metadata.json
gocomics_downloader-1.1.1.3.dist-info/top_level.txt
gocomics_downloader-1.1.1.3.dist-info/zip-safe
