Metadata-Version: 2.0
Name: gocomics-downloader
Version: 1.1.1.3
Summary: Conveniently download the comic images from GoComics comic files. 
Home-page: https://github.com/PokestarFan/GoComics-Downloader
Author: PokestarFan
Author-email: pokestarfan@yahoo.com
License: MIT
Platform: UNKNOWN
Requires-Dist: BeautifulSoup4
Requires-Dist: requests
Requires-Dist: lxml
Requires-Dist: mainchecker
